aioscraper/__init__.py
aioscraper/exceptions.py
aioscraper/_helpers/__init__.py
aioscraper/_helpers/asyncio.py
aioscraper/_helpers/func.py
aioscraper/_helpers/http.py
aioscraper/_helpers/log.py
aioscraper/_helpers/module.py
aioscraper/cli/__init__.py
aioscraper/cli/__main__.py
aioscraper/cli/_args.py
aioscraper/cli/_entrypoint.py
aioscraper/config/__init__.py
aioscraper/config/env.py
aioscraper/config/field_validators.py
aioscraper/config/loader.py
aioscraper/config/model_validator.py
aioscraper/config/models.py
aioscraper/core/__init__.py
aioscraper/core/executor.py
aioscraper/core/pipeline.py
aioscraper/core/rate_limiter.py
aioscraper/core/request_manager.py
aioscraper/core/runner.py
aioscraper/core/scraper.py
aioscraper/core/session/__init__.py
aioscraper/core/session/aiohttp.py
aioscraper/core/session/base.py
aioscraper/core/session/factory.py
aioscraper/core/session/httpx.py
aioscraper/holders/__init__.py
aioscraper/holders/middleware.py
aioscraper/holders/pipeline.py
aioscraper/middlewares/__init__.py
aioscraper/middlewares/retry.py
aioscraper/types/__init__.py
aioscraper/types/middleware.py
aioscraper/types/pipeline.py
aioscraper/types/scraper.py
aioscraper/types/session.py
aioscraper/types/stub.py
aioscraper-0.10.4.dist-info/licenses/LICENSE
aioscraper-0.10.4.dist-info/METADATA
aioscraper-0.10.4.dist-info/WHEEL
aioscraper-0.10.4.dist-info/entry_points.txt
aioscraper-0.10.4.dist-info/top_level.txt
aioscraper-0.10.4.dist-info/RECORD
