Metadata-Version: 2.4
Name: aioscraper
Version: 0.10.4
Summary: High-performance asynchronous Python framework for orchestrating API data collection with clean, modular components.
Author: darkstussy
Project-URL: Homepage, https://github.com/darkstussy/aioscraper
Project-URL: Issues, https://github.com/darkstussy/aioscraper/issues
Classifier: Programming Language :: Python :: 3
Classifier: Programming Language :: Python :: 3.11
Classifier: Programming Language :: Python :: 3.12
Classifier: Programming Language :: Python :: 3.13
Classifier: Programming Language :: Python :: 3.14
Classifier: Framework :: AsyncIO
Classifier: Intended Audience :: Developers
Classifier: Operating System :: OS Independent
Classifier: Topic :: Internet :: WWW/HTTP :: Indexing/Search
Classifier: Topic :: Software Development :: Libraries :: Application Frameworks
Requires-Python: >=3.11
License-File: LICENSE
Requires-Dist: aiojobs~=1.4.0
Requires-Dist: yarl~=1.22.0
Provides-Extra: uvloop
Requires-Dist: uvloop~=0.22.1; extra == "uvloop"
Provides-Extra: aiohttp
Requires-Dist: aiohttp~=3.13.2; extra == "aiohttp"
Provides-Extra: aiohttp-speedups
Requires-Dist: aiohttp[speedups]~=3.13.2; extra == "aiohttp-speedups"
Provides-Extra: httpx
Requires-Dist: httpx~=0.28.1; extra == "httpx"
Dynamic: license-file
